Workbook

Sheet Summary
A1: Property Details | D1: Floor Details | G1: Stabilized Other Income | J1: Stabilized Operating Expenses | P1: Property Tax Growth Rate
A2: # of Units | B2: 100 | D2: Floor | E2: Net Rentable SF | G2: Item | H2: $/Unit/Month | J2: Expenses | K2: Unit/Year | L2: Total | M2: % Fixed | P2: 1 | Q2: =+P2+1 -> 2 | R2: =+Q2+1 -> 3 | S2: =+R2+1 -> 4 | T2: =+S2+1 -> 5 | U2: =+T2+1 -> 6 | V2: =+U2+1 -> 7 | W2: =+V2+1 -> 8 | X2: =+W2+1 -> 9 | Y2: =+X2+1 -> 10
A3: Floors | B3: 48 | D3: 1 | E3: 10000 | G3: Application Fees | H3: 5 | J3: Payroll | K3: 1500 | L3: =+K3*$B$2 -> 150000 | M3: 0.8 | O3: Property Taxes | P3: 0.5 | Q3: 0.25 | R3: 0.03 | S3: 0.03 | T3: 0.03 | U3: 0.03 | V3: 0.03 | W3: 0.03 | X3: 0.03 | Y3: 0.03
A4: Street Address | B4: 845 Texas Ave | D4: =+D3+1 -> 2 | E4: 10000 | G4: Late Fees | H4: 5 | J4: General & Administrative | K4: 250 | L4: =+K4*$B$2 -> 25000 | M4: 0.5 | O4: Fixed Charge Assessments | P4: 0.1 | Q4: 0.05 | R4: 0.03 | S4: 0.03 | T4: 0.03 | U4: 0.03 | V4: 0.03 | W4: 0.03 | X4: 0.03 | Y4: 0.03
A5: City/State/Zip | B5: Houston, Texas, 77002 | D5: =+D4+1 -> 3 | E5: 10000 | G5: Pet Rent | H5: 15 | J5: Marketing | K5: 250 | L5: =+K5*$B$2 -> 25000 | M5: 1
D6: =+D5+1 -> 4 | E6: 10000 | G6: Pet Fees | H6: 5 | J6: Repairs & Maintenance | K6: 400 | L6: =+K6*$B$2 -> 40000 | M6: 0.3 | P6: Hold Period Property Taxes
D7: =+D6+1 -> 5 | E7: 10000 | G7: Garage Income | H7: 20 | J7: Turnover Costs | K7: 300 | L7: =+K7*$B$2 -> 30000 | M7: 0 | P7: 1 | Q7: =+P7+1 -> 2 | R7: =+Q7+1 -> 3 | S7: =+R7+1 -> 4 | T7: =+S7+1 -> 5 | U7: =+T7+1 -> 6 | V7: =+U7+1 -> 7 | W7: =+V7+1 -> 8 | X7: =+W7+1 -> 9 | ... Z7: =+Y7+1 -> 11
D8: =+D7+1 -> 6 | E8: 10000 | G8: Storage Income | H8: 5 | J8: Contract Services | K8: 50 | L8: =+K8*$B$2 -> 5000 | M8: 0.8 | O8: Property Taxes | P8: 100000 | Q8: =+P8*(1+P3) -> 150000 | R8: =+Q8*(1+Q3) -> 187500 | S8: =+R8*(1+R3) -> 193125 | T8: =+S8*(1+S3) -> 198918.75 | U8: =+T8*(1+T3) -> 204886.31 | V8: =+U8*(1+U3) -> 211032.9 | W8: =+V8*(1+V3) -> 217363.89 | X8: =+W8*(1+W3) -> 223884.81 | ... Z8: =+Y8*(1+Y3) -> 237519.39
D9: =+D8+1 -> 7 | E9: 10000 | G9: Other | H9: 0 | J9: Utilities | K9: 200 | L9: =+K9*$B$2 -> 20000 | M9: 0.2 | O9: Fixed Charge Assessments | P9: 5000 | Q9: =+P9*(1+P4) -> 5500 | R9: =+Q9*(1+Q4) -> 5775 | S9: =+R9*(1+R4) -> 5948.25 | T9: =+S9*(1+S4) -> 6126.6975 | U9: =+T9*(1+T4) -> 6310.4984 | V9: =+U9*(1+U4) -> 6499.8134 | W9: =+V9*(1+V4) -> 6694.8078 | X9: =+W9*(1+W4) -> 6895.652 | ... Z9: =+Y9*(1+Y4) -> 7315.5972
D10: =+D9+1 -> 8 | E10: 10000 | G10: Other | H10: 0 | J10: Utility Billback | K10: -25 | L10: =+K10*$B$2 -> -2500 | M10: 0
D11: =+D10+1 -> 9 | E11: 10000 | G11: Other | H11: 0 | J11: Insurance | K11: 400 | L11: =+K11*$B$2 -> 40000 | M11: 1
D12: =+D11+1 -> 10 | E12: 10000 | G12: Other | H12: 0 | J12: Total | K12: =+SUM(K3:K11) -> 3325 | L12: =+SUM(L3:L11) -> 332500 | M12: =+IFERROR(SUMPRODUCT(L3:L11,M3:M11)/L12,0) -> 0.65413534
D13: =+D12+1 -> 11 | E13: 10000 | G13: Other | H13: 0
D14: =+D13+1 -> 12 | E14: 10000 | G14: Other | H14: 0 | J14: Other Expense Assumptions
D15: =+D14+1 -> 13 | E15: 10000 | G15: Total | H15: =+SUM(H3:H14) -> 55 | J15: Annual Expense Growth | K15: 0.03
D16: =+D15+1 -> 14 | E16: 10000 | J16: Capital Expense Reserve/Unit | K16: 250
D17: =+D16+1 -> 15 | E17: 10000 | J17: Property Management Fee (as % of EGR) | K17: 0.03
D18: =+D17+1 -> 16 | E18: 10000
D19: =+D18+1 -> 17 | E19: 10000 | J19: Property Tax Information
D20: =+D19+1 -> 18 | E20: 10000 | J20: Milage Rate | K20: 0.01
D21: =+D20+1 -> 19 | E21: 10000 | J21: Reassessed Upon Sale | K21: No
D22: =+D21+1 -> 20 | E22: 10000 | J22: % of Value Assessed | K22: 1
D23: =+D22+1 -> 21 | E23: 10000
D24: =+D23+1 -> 22 | E24: 10000
D25: =+D24+1 -> 23 | E25: 10000
D26: =+D25+1 -> 24 | E26: 10000
D27: =+D26+1 -> 25 | E27: 10000
D28: =+D27+1 -> 26 | E28: 10000
D29: =+D28+1 -> 27 | E29: 10000
D30: =+D29+1 -> 28 | E30: 10000
D31: =+D30+1 -> 29 | E31: 10000
D32: =+D31+1 -> 30 | E32: 10000
D33: =+D32+1 -> 31 | E33: 10000
D34: =+D33+1 -> 32 | E34: 10000
... D50: =+D49+1 -> 48 | E50: 10000

Sheet Rent Roll
A1: Rent Roll
A2: Suite/Room | C2: Tenant | E2: Lease | I2: Terms | M2: Other
A3: Floor | B3: Number | C3: Tenant Name | D3: SF | E3: Base Rent (Month) | F3: Lease Type | G3: Lease Start | H3: Lease Expiration | I3: Guarantor | J3: Rent Abatements | K3: Tenant Improvements | L3: Fees | M3: Lease Term Notes
A4: 2 | B4: 201 | C4: The SQ | D4: 10000 | E4: 2400 | F4: Gross | G4: 44562 | H4: 47118 | I4: None | J4: 0 | K4: 0 | L4: =+Summary!$H$15 -> 55 | M4: None
A5: 12 | B5: 1201 | C5: The SQ | D5: 2500 | E5: 2400 | F5: Gross | G5: 44562 | H5: 47118 | I5: None | J5: 0 | K5: 0 | L5: =+Summary!$H$15 -> 55 | M5: None
A6: 12 | B6: 1202 | C6: Cheniere | D6: 4444 | E6: 2400 | F6: Gross | G6: 44562 | H6: 47118 | I6: None | J6: 0 | K6: 0 | L6: =+Summary!$H$15 -> 55 | M6: None
A7: 13 | B7: 1301 | C7: Cheniere | D7: 10000 | E7: 2400 | F7: Gross | G7: 44562 | H7: 47118 | I7: None | J7: 0 | K7: 0 | L7: =+Summary!$H$15 -> 55 | M7: None
A8: 14 | B8: 1401 | C8: Cheniere | D8: 10000 | E8: 2400 | F8: Gross | G8: 44562 | H8: 47118 | I8: None | J8: 0 | K8: 0 | L8: =+Summary!$H$15 -> 55 | M8: None
A9: 15 | B9: 1501 | C9: Cheniere | D9: 10000 | E9: 2400 | F9: Gross | G9: 44562 | H9: 47118 | I9: None | J9: 0 | K9: 0 | L9: =+Summary!$H$15 -> 55 | M9: None
A10: 16 | B10: 1601 | C10: Cheniere | D10: 10000 | E10: 2400 | F10: Gross | G10: 44562 | H10: 47118 | I10: None | J10: 0 | K10: 0 | L10: =+Summary!$H$15 -> 55 | M10: None
A11: 18 | B11: 1801 | C11: Squarepoint Capital | D11: 2278 | E11: 2400 | F11: Gross | G11: 44562 | H11: 47118 | I11: None | J11: 0 | K11: 0 | L11: =+Summary!$H$15 -> 55 | M11: None
A12: 22 | B12: 2201 | C12: Moelis & Company | D12: 8400 | E12: 2400 | F12: Gross | G12: 44562 | H12: 47118 | I12: None | J12: 0 | K12: 0 | L12: =+Summary!$H$15 -> 55 | M12: None
A13: 25 | B13: 2501 | C13: Sheppard Mullin | D13: 8200 | E13: 2400 | F13: Gross | G13: 44562 | H13: 47118 | I13: None | J13: 0 | K13: 0 | L13: =+Summary!$H$15 -> 55 | M13: None
A14: 28 | B14: 2801 | C14: Sable Offshore Corp | D14: 10000 | E14: 2400 | F14: Gross | G14: 44562 | H14: 47118 | I14: None | J14: 0 | K14: 0 | L14: =+Summary!$H$15 -> 55 | M14: None
A15: 29 | B15: 2901 | C15: Sable Offshore Corp | D15: 2778 | E15: 2400 | F15: Gross | G15: 44562 | H15: 47118 | I15: None | J15: 0 | K15: 0 | L15: =+Summary!$H$15 -> 55 | M15: None
... A28: 47 | B28: 4701 | C28: Vinson & Elkins | D28: 10000 | E28: 2400 | F28: Gross | G28: 44562 | H28: 47118 | I28: None | J28: 0 | K28: 0 | L28: =+Summary!$H$15 -> 55 | M28: None
